<layer>
  <name>OK_DIRT_VIEW</name>
  <id>LayerInfoImpl--42fee024:14252c3d422:-72c4</id>
  <type>VECTOR</type>
  <defaultStyle>
    <id>StyleInfoImpl--42fee024:1424f42a501:-3c0f</id>
  </defaultStyle>
  <styles class="linked-hash-set">
    <style>
      <id>StyleInfoImpl--42fee024:1424f42a501:-3c0f</id>
    </style>
  </styles>
  <resource class="featureType">
    <id>FeatureTypeInfoImpl--42fee024:14252c3d422:-72c5</id>
  </resource>
  <attribution>
    <logoWidth>0</logoWidth>
    <logoHeight>0</logoHeight>
  </attribution>
</layer>